email_report_checker/__init__.py
email_report_checker/dmarc.py
email_report_checker/py.typed
email_report_checker/tls.py
email_report_checker/util.py
email_report_checker-0.0.1.dist-info/LICENSE
email_report_checker-0.0.1.dist-info/METADATA
email_report_checker-0.0.1.dist-info/WHEEL
email_report_checker-0.0.1.dist-info/entry_points.txt
email_report_checker-0.0.1.dist-info/top_level.txt
email_report_checker-0.0.1.dist-info/RECORD
