Metadata-Version: 2.1
Name: email-report-checker
Version: 0.0.1
Summary: RFC 7489 & 8460 SMTP Report Monitoring Utilities.
Home-page: UNKNOWN
Author: Barnaby Shearer
Author-email: b@zi.is
License: UNKNOWN
Project-URL: Source, https://github.com/BarnabyShearer/email-report-checker
Project-URL: Tracker, https://github.com/BarnabyShearer/email-report-checker/issues
Project-URL: Documentation, https://email-report-checker.readthedocs.io/en/latest/
Keywords: dmarc email smtp tls
Platform: UNKNOWN
Classifier: Development Status :: 5 - Production/Stable
Classifier: License :: OSI Approved :: BSD License
Classifier: Programming Language :: Python :: 3
Requires-Python: >=3.7
License-File: LICENSE
